bonito.py
bonito-0.2.dist-info/METADATA
bonito-0.2.dist-info/WHEEL
bonito-0.2.dist-info/entry_points.txt
bonito-0.2.dist-info/top_level.txt
bonito-0.2.dist-info/zip-safe
bonito-0.2.dist-info/RECORD
