Metadata-Version: 2.1
Name: bonito
Version: 0.2
Summary: Generate a print & cut numerated tickets in PDF from a SVG template
Home-page: http://mgaitan.github.io/posts/bonito-feito-pero-efectivo/
Author: Martín Gaitán
Author-email: gaitan@gmail.com
License: BSD
Platform: UNKNOWN
Classifier: Development Status :: 4 - Beta
Classifier: Intended Audience :: Education
Classifier: License :: OSI Approved :: BSD License
Classifier: Programming Language :: Python :: 3.6
Classifier: Programming Language :: Python :: 3.7
Requires-Dist: docopt
